sage/__init__.py
sage/cli.py
sage/Core/__init__.py
sage/Core/api.py
sage/Core/chat.py
sage/Core/combiner.py
sage/Core/env_util.py
sage/Core/models.py
sage/Core/orchestrator.py
sage/Core/prompts.py
sage/Core/select_models.py
sage/Starters/AI_summerize.py
sage/Starters/__init__.py
sage/Starters/common_ignors.py
sage/Starters/entry.py
sage/Starters/env_utils.py
sage/Starters/file_utils.py
sage/Starters/prompts.py
sage/Starters/summerizer.py
sage/Starters/terminals.py
sage_code-0.1.4.dist-info/METADATA
sage_code-0.1.4.dist-info/WHEEL
sage_code-0.1.4.dist-info/entry_points.txt
sage_code-0.1.4.dist-info/top_level.txt
sage_code-0.1.4.dist-info/RECORD
