Metadata-Version: 2.4
Name: sage-code
Version: 0.1.4
Summary: A senior developer in your terminal.
Author-email: "Fikresilase W. Abebayew" <shitubilbila@gmail.com>
License: MIT
Project-URL: homepage, https://github.com/Fikresilase/sage
Project-URL: repository, https://github.com/Fikresilase/sage
Project-URL: bugtracker, https://github.com/Fikresilase/sage/issues
Keywords: cli,ai,assistant,developer-tools,claude code alternative,codex alternative,open source,productivity
Requires-Python: >=3.12
Requires-Dist: typer>=0.9.0
Requires-Dist: rich>=13.0.0
Requires-Dist: inquirer>=3.0.0
Requires-Dist: openai>=1.0.0
Requires-Dist: prompt_toolkit>=3.0.0
